wire_memory/__init__.py
wire_memory/client.py
wire_memory/py.typed
wire_memory/server.py
wire_memory-0.7.1.dist-info/WHEEL
wire_memory-0.7.1.dist-info/METADATA
wire_memory-0.7.1.dist-info/RECORD
