Metadata-Version: 2.3
Name: wire_memory
Version: 0.7.1
Summary: Wire for communicating over memory
Keywords: crdt
Author: David Brochart
Author-email: David Brochart <david.brochart@gmail.com>
License: The MIT License (MIT)
Classifier: Development Status :: 4 - Beta
Classifier: Intended Audience :: Developers
Classifier: License :: OSI Approved :: MIT License
Classifier: Programming Language :: Python
Classifier: Programming Language :: Python :: 3.10
Classifier: Programming Language :: Python :: 3.11
Classifier: Programming Language :: Python :: 3.12
Classifier: Programming Language :: Python :: 3.13
Classifier: Programming Language :: Python :: 3.14
Classifier: Programming Language :: Python :: Implementation :: CPython
Classifier: Programming Language :: Python :: Implementation :: PyPy
Requires-Dist: wiredb>=0.7.0,<0.8.0
Requires-Python: >=3.10
Project-URL: Homepage, https://github.com/davidbrochart/wiredb
